object_last_modified/object_last_modified/manifest.toml
object_last_modified/object_last_modified/object_last_modified.py
object_last_modified/object_last_modified/object_last_modified.rego
object_last_modified/object_last_modified/test_object_last_modified.py
storage_class_usage/storage_class_usage/manifest.toml
storage_class_usage/storage_class_usage/storage_class_usage.py
storage_class_usage/storage_class_usage/storage_class_usage.rego
storage_class_usage/storage_class_usage/test_storage_class_usage.py
unused_buckets/unused_buckets/manifest.toml
unused_buckets/unused_buckets/test_unused_buckets.py
unused_buckets/unused_buckets/unused_buckets.py
unused_buckets/unused_buckets/unused_buckets.rego
opsbox_s3_checks-0.2.0.dist-info/LICENCE.txt
opsbox_s3_checks-0.2.0.dist-info/METADATA
opsbox_s3_checks-0.2.0.dist-info/WHEEL
opsbox_s3_checks-0.2.0.dist-info/entry_points.txt
opsbox_s3_checks-0.2.0.dist-info/top_level.txt
opsbox_s3_checks-0.2.0.dist-info/RECORD
