Metadata-Version: 2.2
Name: opsbox-s3-checks
Version: 0.2.0
Summary: Collection of S3 checks for opsbox
Requires-Python: ==3.11.*
License-File: LICENCE.txt
Requires-Dist: opsbox-s3-provider>=0.1.3
Requires-Dist: opsbox-rego-handler>=0.2.0
